nfetoolkit/__init__.py
nfetoolkit/cli.py
nfetoolkit/fix.py
nfetoolkit/handler.py
nfetoolkit/organizer.py
nfetoolkit/repository.py
nfetoolkit-0.3.3.dist-info/licenses/LICENSE
nfetoolkit-0.3.3.dist-info/METADATA
nfetoolkit-0.3.3.dist-info/WHEEL
nfetoolkit-0.3.3.dist-info/entry_points.txt
nfetoolkit-0.3.3.dist-info/top_level.txt
nfetoolkit-0.3.3.dist-info/RECORD
