Metadata-Version: 2.4
Name: nfetoolkit
Version: 0.3.3
Summary: Toolkit para manipulação de notas fiscais eletrônicas
Home-page: https://github.com/ismaelnjr/nfetoolkit-project.git
Author: Ismael Nascimento
Author-email: ismaelnjr@icloud.com.br
License: MIT
Classifier: Programming Language :: Python :: 3
Classifier: License :: OSI Approved :: MIT License
Classifier: Operating System :: OS Independent
Requires-Python: >=3.9
License-File: LICENSE
Requires-Dist: nfelib
Requires-Dist: spedpy
Requires-Dist: tqdm
Requires-Dist: xsdata
Requires-Dist: lxml
Dynamic: author
Dynamic: author-email
Dynamic: classifier
Dynamic: description
Dynamic: description-content-type
Dynamic: home-page
Dynamic: license
Dynamic: license-file
Dynamic: requires-dist
Dynamic: requires-python
Dynamic: summary
